{
  "Product": {
    "ProductNo": "7257",
    "ProductName": "Ultimate Lightsaber™ Duel",
    "ItemNo": "4250415",
    "Asset": "/images/shop/prod/7257-0000-xx-12-1.jpg"
  },
  "Bricks": [
    {
      "ItemNo": 611126,
      "ItemDescr": "BRICK 1X10",
      "ColourLikeDescr": "Black",
      "ColourDescr": "BLACK",
      "MaingroupDescr": "Bricks, Special",
      "Asset": "/media/bricks/5/2/611126.jpg",
      "MaxQty": 200,
      "Ip": false,
      "Price": 0.43,
      "CId": "GBP",
      "SQty": 1364,
      "DesignId": 6111,
      "PriceStr": "GBP 0.43",
      "PriceWithTaxStr": "GBP 0.43",
      "ItemUnavailable": false,
      "UnavailableLink": null,
      "UnavailableReason": null
    },
    {
      "ItemNo": 301026,
      "ItemDescr": "BRICK 1X4",
      "ColourLikeDescr": "Black",
      "ColourDescr": "BLACK",
      "MaingroupDescr": "Bricks, Special",
      "Asset": "/media/bricks/5/2/301026.jpg",
      "MaxQty": 200,
      "Ip": false,
      "Price": 0.14,
      "CId": "GBP",
      "SQty": 9952,
      "DesignId": 3010,
      "PriceStr": "GBP 0.14",
      "PriceWithTaxStr": "GBP 0.14",
      "ItemUnavailable": false,
      "UnavailableLink": null,
      "UnavailableReason": null
    },
    {
      "ItemNo": 4617860,
      "ItemDescr": "BRICK 2X10",
      "ColourLikeDescr": "Black",
      "ColourDescr": "BLACK",
      "MaingroupDescr": "Bricks, Special",
      "Asset": "/media/bricks/5/2/4617860.jpg",
      "MaxQty": 200,
      "Ip": false,
      "Price": 0.58,
      "CId": "GBP",
      "SQty": 1385,
      "DesignId": 92538,
      "PriceStr": "GBP 0.58",
      "PriceWithTaxStr": "GBP 0.58",
      "ItemUnavailable": false,
      "UnavailableLink": null,
      "UnavailableReason": null
    },
    {
      "ItemNo": 302226,
      "ItemDescr": "PLATE 2X2",
      "ColourLikeDescr": "Black",
      "ColourDescr": "BLACK",
      "MaingroupDescr": "Bricks, Special",
      "Asset": "/media/bricks/5/2/302226.jpg",
      "MaxQty": 200,
      "Ip": false,
      "Price": 0.07,
      "CId": "GBP",
      "SQty": 8292,
      "DesignId": 3022,
      "PriceStr": "GBP 0.07",
      "PriceWithTaxStr": "GBP 0.07",
      "ItemUnavailable": false,
      "UnavailableLink": null,
      "UnavailableReason": null
    },
    {
      "ItemNo": 300226,
      "ItemDescr": "BRICK 2X3",
      "ColourLikeDescr": "Black",
      "ColourDescr": "BLACK",
      "MaingroupDescr": "Bricks, Special",
      "Asset": "/media/bricks/5/2/300226.jpg",
      "MaxQty": 200,
      "Ip": false,
      "Price": 0.17,
      "CId": "GBP",
      "SQty": 4777,
      "DesignId": 3002,
      "PriceStr": "GBP 0.17",
      "PriceWithTaxStr": "GBP 0.17",
      "ItemUnavailable": false,
      "UnavailableLink": null,
      "UnavailableReason": null
    },
    {
      "ItemNo": 4113241,
      "ItemDescr": "BRICK 2X2X3",
      "ColourLikeDescr": "Black",
      "ColourDescr": "BLACK",
      "MaingroupDescr": "Bricks, Special",
      "Asset": "/media/bricks/5/2/4113241.jpg",
      "MaxQty": 200,
      "Ip": false,
      "Price": 0.48,
      "CId": "GBP",
      "SQty": 562,
      "DesignId": 30145,
      "PriceStr": "GBP 0.48",
      "PriceWithTaxStr": "GBP 0.48",
      "ItemUnavailable": false,
      "UnavailableLink": null,
      "UnavailableReason": null
    },
    {
      "ItemNo": 300326,
      "ItemDescr": "BRICK 2X2",
      "ColourLikeDescr": "Black",
      "ColourDescr": "BLACK",
      "MaingroupDescr": "Bricks, Special",
      "Asset": "/media/bricks/5/2/300326.jpg",
      "MaxQty": 200,
      "Ip": false,
      "Price": 0.11,
      "CId": "GBP",
      "SQty": 5818,
      "DesignId": 3003,
      "PriceStr": "GBP 0.11",
      "PriceWithTaxStr": "GBP 0.11",
      "ItemUnavailable": false,
      "UnavailableLink": null,
      "UnavailableReason": null
    },
    {
      "ItemNo": 300126,
      "ItemDescr": "BRICK 2X4",
      "ColourLikeDescr": "Black",
      "ColourDescr": "BLACK",
      "MaingroupDescr": "Bricks, Special",
      "Asset": "/media/bricks/5/2/300126.jpg",
      "MaxQty": 200,
      "Ip": false,
      "Price": 0.2,
      "CId": "GBP",
      "SQty": 25240,
      "DesignId": 3001,
      "PriceStr": "GBP 0.20",
      "PriceWithTaxStr": "GBP 0.20",
      "ItemUnavailable": false,
      "UnavailableLink": null,
      "UnavailableReason": null
    },
    {
      "ItemNo": 300826,
      "ItemDescr": "BRICK 1X8",
      "ColourLikeDescr": "Black",
      "ColourDescr": "BLACK",
      "MaingroupDescr": "Bricks, Special",
      "Asset": "/media/bricks/5/2/300826.jpg",
      "MaxQty": 200,
      "Ip": false,
      "Price": 0.29,
      "CId": "GBP",
      "SQty": 3937,
      "DesignId": 3008,
      "PriceStr": "GBP 0.29",
      "PriceWithTaxStr": "GBP 0.29",
      "ItemUnavailable": false,
      "UnavailableLink": null,
      "UnavailableReason": null
    },
    {
      "ItemNo": 302026,
      "ItemDescr": "PLATE 2X4",
      "ColourLikeDescr": "Black",
      "ColourDescr": "BLACK",
      "MaingroupDescr": "Bricks, Special",
      "Asset": "/media/bricks/5/2/302026.jpg",
      "MaxQty": 200,
      "Ip": false,
      "Price": 0.12,
      "CId": "GBP",
      "SQty": 2413,
      "DesignId": 3020,
      "PriceStr": "GBP 0.12",
      "PriceWithTaxStr": "GBP 0.12",
      "ItemUnavailable": false,
      "UnavailableLink": null,
      "UnavailableReason": null
    },
    {
      "ItemNo": 4233487,
      "ItemDescr": "BRICK 1X2 WITH CROSS HOLE",
      "ColourLikeDescr": "Black",
      "ColourDescr": "BLACK",
      "MaingroupDescr": "Bricks, Special",
      "Asset": "/media/bricks/5/2/4233487.jpg",
      "MaxQty": 200,
      "Ip": false,
      "Price": 0.17,
      "CId": "GBP",
      "SQty": 871,
      "DesignId": 32064,
      "PriceStr": "GBP 0.17",
      "PriceWithTaxStr": "GBP 0.17",
      "ItemUnavailable": false,
      "UnavailableLink": null,
      "UnavailableReason": null
    },
    {
      "ItemNo": 403226,
      "ItemDescr": "PLATE 2X2 ROUND",
      "ColourLikeDescr": "Black",
      "ColourDescr": "BLACK",
      "MaingroupDescr": "Bricks, Special",
      "Asset": "/media/bricks/5/2/403226.jpg",
      "MaxQty": 200,
      "Ip": false,
      "Price": 0.07,
      "CId": "GBP",
      "SQty": 10422,
      "DesignId": 4032,
      "PriceStr": "GBP 0.07",
      "PriceWithTaxStr": "GBP 0.07",
      "ItemUnavailable": false,
      "UnavailableLink": null,
      "UnavailableReason": null
    },
    {
      "ItemNo": 4260510,
      "ItemDescr": "VÆGELEMENT 2X4X6 199/47/199",
      "ColourLikeDescr": "",
      "ColourDescr": "2.MULT",
      "MaingroupDescr": "Bricks, Special",
      "Asset": "/media/bricks/4/2/4260510.jpg",
      "MaxQty": 200,
      "Ip": false,
      "Price": -1,
      "CId": "GBP",
      "SQty": 0,
      "DesignId": 47847,
      "PriceStr": "",
      "PriceWithTaxStr": "",
      "ItemUnavailable": false,
      "UnavailableLink": null,
      "UnavailableReason": null
    },
    {
      "ItemNo": 4142995,
      "ItemDescr": "PARABOLIC ELEMENT Ø16 - TR",
      "ColourLikeDescr": "Red",
      "ColourDescr": "TR.RED",
      "MaingroupDescr": "Bricks, Special",
      "Asset": "/media/bricks/5/2/4142995.jpg",
      "MaxQty": 200,
      "Ip": false,
      "Price": 0.08,
      "CId": "GBP",
      "SQty": 3498,
      "DesignId": 30063,
      "PriceStr": "GBP 0.08",
      "PriceWithTaxStr": "GBP 0.08",
      "ItemUnavailable": false,
      "UnavailableLink": null,
      "UnavailableReason": null
    },
    {
      "ItemNo": 3005747,
      "ItemDescr": "ROUND PLATE 1X1 - TR.",
      "ColourLikeDescr": "",
      "ColourDescr": "TR.FL.REDORA",
      "MaingroupDescr": "Bricks, Special",
      "Asset": "/media/bricks/5/2/3005747.jpg",
      "MaxQty": 200,
      "Ip": false,
      "Price": 0.05,
      "CId": "GBP",
      "SQty": 6148,
      "DesignId": 30057,
      "PriceStr": "GBP 0.05",
      "PriceWithTaxStr": "GBP 0.05",
      "ItemUnavailable": false,
      "UnavailableLink": null,
      "UnavailableReason": null
    },
    {
      "ItemNo": 4260403,
      "ItemDescr": "CORNER PLATE 3X6 PC/TR",
      "ColourLikeDescr": "",
      "ColourDescr": "TR.FL.REDORA",
      "MaingroupDescr": "Bricks, Special",
      "Asset": "/media/bricks/5/2/4260403.jpg",
      "MaxQty": 200,
      "Ip": false,
      "Price": -1,
      "CId": "GBP",
      "SQty": 0,
      "DesignId": 43127,
      "PriceStr": "",
      "PriceWithTaxStr": "",
      "ItemUnavailable": false,
      "UnavailableLink": null,
      "UnavailableReason": null
    },
    {
      "ItemNo": 4204537,
      "ItemDescr": "FLAT TILE 1X2 - TR",
      "ColourLikeDescr": "",
      "ColourDescr": "TR.FL.REDORA",
      "MaingroupDescr": "Bricks, Special",
      "Asset": "/media/bricks/5/2/4204537.jpg",
      "MaxQty": 200,
      "Ip": false,
      "Price": -1,
      "CId": "GBP",
      "SQty": 0,
      "DesignId": 30070,
      "PriceStr": "",
      "PriceWithTaxStr": "",
      "ItemUnavailable": false,
      "UnavailableLink": null,
      "UnavailableReason": null
    },
    {
      "ItemNo": 4153989,
      "ItemDescr": "ROUND BRICK 1 - TR",
      "ColourLikeDescr": "",
      "ColourDescr": "TR.FL.REDORA",
      "MaingroupDescr": "Bricks, Special",
      "Asset": "/media/bricks/5/2/4153989.jpg",
      "MaxQty": 200,
      "Ip": false,
      "Price": 0.1,
      "CId": "GBP",
      "SQty": 1209,
      "DesignId": 30068,
      "PriceStr": "GBP 0.10",
      "PriceWithTaxStr": "GBP 0.10",
      "ItemUnavailable": false,
      "UnavailableLink": null,
      "UnavailableReason": null
    },
    {
      "ItemNo": 612647,
      "ItemDescr": "DRAGON'S FIRE",
      "ColourLikeDescr": "",
      "ColourDescr": "TR.FL.REDORA",
      "MaingroupDescr": "Bricks, Special",
      "Asset": "/media/bricks/5/2/612647.jpg",
      "MaxQty": 200,
      "Ip": false,
      "Price": 0.11,
      "CId": "GBP",
      "SQty": 4020,
      "DesignId": 6126,
      "PriceStr": "GBP 0.11",
      "PriceWithTaxStr": "GBP 0.11",
      "ItemUnavailable": false,
      "UnavailableLink": null,
      "UnavailableReason": null
    },
    {
      "ItemNo": 4260487,
      "ItemDescr": "PLATE 8X8 PC/TR",
      "ColourLikeDescr": "",
      "ColourDescr": "TR.FL.REDORA",
      "MaingroupDescr": "Bricks, Special",
      "Asset": "/media/bricks/5/2/4260487.jpg",
      "MaxQty": 200,
      "Ip": false,
      "Price": -1,
      "CId": "GBP",
      "SQty": 0,
      "DesignId": 42534,
      "PriceStr": "",
      "PriceWithTaxStr": "",
      "ItemUnavailable": false,
      "UnavailableLink": null,
      "UnavailableReason": null
    },
    {
      "ItemNo": 6124909,
      "ItemDescr": "SLIDE SHOE ROUND 2X2",
      "ColourLikeDescr": "",
      "ColourDescr": "TR.FL.REDORA",
      "MaingroupDescr": "Bricks, Special",
      "Asset": "/media/bricks/5/2/6124909.jpg",
      "MaxQty": 200,
      "Ip": false,
      "Price": 0.14,
      "CId": "GBP",
      "SQty": 1270,
      "DesignId": 54196,
      "PriceStr": "GBP 0.14",
      "PriceWithTaxStr": "GBP 0.14",
      "ItemUnavailable": false,
      "UnavailableLink": null,
      "UnavailableReason": null
    },
    {
      "ItemNo": 4260478,
      "ItemDescr": "ROUND PLATE 1X1",
      "ColourLikeDescr": "",
      "ColourDescr": "SILVER",
      "MaingroupDescr": "Bricks, Special",
      "Asset": "/media/bricks/5/2/4260478.jpg",
      "MaxQty": 200,
      "Ip": false,
      "Price": -1,
      "CId": "GBP",
      "SQty": 0,
      "DesignId": 6141,
      "PriceStr": "",
      "PriceWithTaxStr": "",
      "ItemUnavailable": false,
      "UnavailableLink": null,
      "UnavailableReason": null
    },
    {
      "ItemNo": 4245463,
      "ItemDescr": "WALL ELEMENT 1X2X1",
      "ColourLikeDescr": "",
      "ColourDescr": "RED. BROWN",
      "MaingroupDescr": "Bricks, Special",
      "Asset": "/media/bricks/5/2/4245463.jpg",
      "MaxQty": 200,
      "Ip": false,
      "Price": -1,
      "CId": "GBP",
      "SQty": 0,
      "DesignId": 4865,
      "PriceStr": "",
      "PriceWithTaxStr": "",
      "ItemUnavailable": false,
      "UnavailableLink": null,
      "UnavailableReason": null
    },
    {
      "ItemNo": 4504376,
      "ItemDescr": "ROOF TILE 1X1X2/3, ABS",
      "ColourLikeDescr": "",
      "ColourDescr": "RED. BROWN",
      "MaingroupDescr": "Bricks, Special",
      "Asset": "/media/bricks/5/2/4504376.jpg",
      "MaxQty": 200,
      "Ip": false,
      "Price": 0.05,
      "CId": "GBP",
      "SQty": 10342,
      "DesignId": 54200,
      "PriceStr": "GBP 0.05",
      "PriceWithTaxStr": "GBP 0.05",
      "ItemUnavailable": false,
      "UnavailableLink": null,
      "UnavailableReason": null
    },
    {
      "ItemNo": 4260407,
      "ItemDescr": "T-BEAM W. PLATE 1X2 W. TUBE",
      "ColourLikeDescr": "",
      "ColourDescr": "RED. BROWN",
      "MaingroupDescr": "Bricks, Special",
      "Asset": "/media/bricks/5/2/4260407.jpg",
      "MaxQty": 200,
      "Ip": false,
      "Price": -1,
      "CId": "GBP",
      "SQty": 0,
      "DesignId": 32530,
      "PriceStr": "",
      "PriceWithTaxStr": "",
      "ItemUnavailable": false,
      "UnavailableLink": null,
      "UnavailableReason": null
    },
    {
      "ItemNo": 4211278,
      "ItemDescr": "FLAT TILE 1X8",
      "ColourLikeDescr": "",
      "ColourDescr": "RED. BROWN",
      "MaingroupDescr": "Bricks, Special",
      "Asset": "/media/bricks/5/2/4211278.jpg",
      "MaxQty": 200,
      "Ip": false,
      "Price": -1,
      "CId": "GBP",
      "SQty": 0,
      "DesignId": 4162,
      "PriceStr": "",
      "PriceWithTaxStr": "",
      "ItemUnavailable": false,
      "UnavailableLink": null,
      "UnavailableReason": null
    },
    {
      "ItemNo": 4645400,
      "ItemDescr": "WALL CORNER 1X1X1",
      "ColourLikeDescr": "",
      "ColourDescr": "RED. BROWN",
      "MaingroupDescr": "Bricks, Special",
      "Asset": "/media/bricks/5/2/4645400.jpg",
      "MaxQty": 200,
      "Ip": false,
      "Price": 0.07,
      "CId": "GBP",
      "SQty": 2642,
      "DesignId": 6231,
      "PriceStr": "GBP 0.07",
      "PriceWithTaxStr": "GBP 0.07",
      "ItemUnavailable": false,
      "UnavailableLink": null,
      "UnavailableReason": null
    },
    {
      "ItemNo": 4211150,
      "ItemDescr": "PLATE 1X2",
      "ColourLikeDescr": "",
      "ColourDescr": "RED. BROWN",
      "MaingroupDescr": "Bricks, Special",
      "Asset": "/media/bricks/5/2/4211150.jpg",
      "MaxQty": 200,
      "Ip": false,
      "Price": 0.05,
      "CId": "GBP",
      "SQty": 17891,
      "DesignId": 3023,
      "PriceStr": "GBP 0.05",
      "PriceWithTaxStr": "GBP 0.05",
      "ItemUnavailable": false,
      "UnavailableLink": null,
      "UnavailableReason": null
    },
    {
      "ItemNo": 4211149,
      "ItemDescr": "BRICK 1X2",
      "ColourLikeDescr": "",
      "ColourDescr": "RED. BROWN",
      "MaingroupDescr": "Bricks, Special",
      "Asset": "/media/bricks/5/2/4211149.jpg",
      "MaxQty": 200,
      "Ip": false,
      "Price": 0.08,
      "CId": "GBP",
      "SQty": 17849,
      "DesignId": 3004,
      "PriceStr": "GBP 0.08",
      "PriceWithTaxStr": "GBP 0.08",
      "ItemUnavailable": false,
      "UnavailableLink": null,
      "UnavailableReason": null
    },
    {
      "ItemNo": 4218742,
      "ItemDescr": "BOWED ROOF RIDGE 2X4X1",
      "ColourLikeDescr": "",
      "ColourDescr": "RED. BROWN",
      "MaingroupDescr": "Bricks, Special",
      "Asset": "/media/bricks/5/2/4218742.jpg",
      "MaxQty": 200,
      "Ip": false,
      "Price": -1,
      "CId": "GBP",
      "SQty": 0,
      "DesignId": 6192,
      "PriceStr": "",
      "PriceWithTaxStr": "",
      "ItemUnavailable": false,
      "UnavailableLink": null,
      "UnavailableReason": null
    },
    {
      "ItemNo": 4219726,
      "ItemDescr": "PLATE 1X2 W. 1 KNOB",
      "ColourLikeDescr": "",
      "ColourDescr": "RED. BROWN",
      "MaingroupDescr": "Bricks, Special",
      "Asset": "/media/bricks/5/2/4219726.jpg",
      "MaxQty": 200,
      "Ip": false,
      "Price": 0.07,
      "CId": "GBP",
      "SQty": 3852,
      "DesignId": 3794,
      "PriceStr": "GBP 0.07",
      "PriceWithTaxStr": "GBP 0.07",
      "ItemUnavailable": false,
      "UnavailableLink": null,
      "UnavailableReason": null
    },
    {
      "ItemNo": 4211194,
      "ItemDescr": "FLAT TILE 1X4",
      "ColourLikeDescr": "",
      "ColourDescr": "RED. BROWN",
      "MaingroupDescr": "Bricks, Special",
      "Asset": "/media/bricks/5/2/4211194.jpg",
      "MaxQty": 200,
      "Ip": false,
      "Price": 0.11,
      "CId": "GBP",
      "SQty": 8360,
      "DesignId": 2431,
      "PriceStr": "GBP 0.11",
      "PriceWithTaxStr": "GBP 0.11",
      "ItemUnavailable": false,
      "UnavailableLink": null,
      "UnavailableReason": null
    },
    {
      "ItemNo": 4211481,
      "ItemDescr": "FLAT TILE 1X8",
      "ColourLikeDescr": "Grey",
      "ColourDescr": "MED. ST-GREY",
      "MaingroupDescr": "Bricks, Special",
      "Asset": "/media/bricks/5/2/4211481.jpg",
      "MaxQty": 200,
      "Ip": false,
      "Price": 0.22,
      "CId": "GBP",
      "SQty": 507,
      "DesignId": 4162,
      "PriceStr": "GBP 0.22",
      "PriceWithTaxStr": "GBP 0.22",
      "ItemUnavailable": false,
      "UnavailableLink": null,
      "UnavailableReason": null
    },
    {
      "ItemNo": 4211568,
      "ItemDescr": "PLATE 1X2 WITH SLIDE",
      "ColourLikeDescr": "Grey",
      "ColourDescr": "MED. ST-GREY",
      "MaingroupDescr": "Bricks, Special",
      "Asset": "/media/bricks/5/2/4211568.jpg",
      "MaxQty": 200,
      "Ip": false,
      "Price": 0.07,
      "CId": "GBP",
      "SQty": 17193,
      "DesignId": 32028,
      "PriceStr": "GBP 0.07",
      "PriceWithTaxStr": "GBP 0.07",
      "ItemUnavailable": false,
      "UnavailableLink": null,
      "UnavailableReason": null
    },
    {
      "ItemNo": 4211414,
      "ItemDescr": "FLAT TILE 1X2",
      "ColourLikeDescr": "Grey",
      "ColourDescr": "MED. ST-GREY",
      "MaingroupDescr": "Bricks, Special",
      "Asset": "/media/bricks/5/2/4211414.jpg",
      "MaxQty": 200,
      "Ip": false,
      "Price": 0.06,
      "CId": "GBP",
      "SQty": 18843,
      "DesignId": 3069,
      "PriceStr": "GBP 0.06",
      "PriceWithTaxStr": "GBP 0.06",
      "ItemUnavailable": false,
      "UnavailableLink": null,
      "UnavailableReason": null
    },
    {
      "ItemNo": 4211356,
      "ItemDescr": "FLAT TILE 1X4",
      "ColourLikeDescr": "Grey",
      "ColourDescr": "MED. ST-GREY",
      "MaingroupDescr": "Bricks, Special",
      "Asset": "/media/bricks/5/2/4211356.jpg",
      "MaxQty": 200,
      "Ip": false,
      "Price": 0.11,
      "CId": "GBP",
      "SQty": 3844,
      "DesignId": 2431,
      "PriceStr": "GBP 0.11",
      "PriceWithTaxStr": "GBP 0.11",
      "ItemUnavailable": false,
      "UnavailableLink": null,
      "UnavailableReason": null
    },
    {
      "ItemNo": 4211460,
      "ItemDescr": "HINGE 1X2 UPPER PART",
      "ColourLikeDescr": "Grey",
      "ColourDescr": "MED. ST-GREY",
      "MaingroupDescr": "Bricks, Special",
      "Asset": "/media/bricks/5/2/4211460.jpg",
      "MaxQty": 200,
      "Ip": false,
      "Price": -1,
      "CId": "GBP",
      "SQty": 0,
      "DesignId": 3830,
      "PriceStr": "",
      "PriceWithTaxStr": "",
      "ItemUnavailable": false,
      "UnavailableLink": null,
      "UnavailableReason": null
    },
    {
      "ItemNo": 4211413,
      "ItemDescr": "FLAT TILE 2X2",
      "ColourLikeDescr": "Grey",
      "ColourDescr": "MED. ST-GREY",
      "MaingroupDescr": "Bricks, Special",
      "Asset": "/media/bricks/5/2/4211413.jpg",
      "MaxQty": 200,
      "Ip": false,
      "Price": 0.07,
      "CId": "GBP",
      "SQty": 5772,
      "DesignId": 3068,
      "PriceStr": "GBP 0.07",
      "PriceWithTaxStr": "GBP 0.07",
      "ItemUnavailable": false,
      "UnavailableLink": null,
      "UnavailableReason": null
    },
    {
      "ItemNo": 4211887,
      "ItemDescr": "STANDARD Ø3.18 X 53",
      "ColourLikeDescr": "Grey",
      "ColourDescr": "MED. ST-GREY",
      "MaingroupDescr": "Bricks, Special",
      "Asset": "/media/bricks/5/2/4211887.jpg",
      "MaxQty": 200,
      "Ip": false,
      "Price": -1,
      "CId": "GBP",
      "SQty": -55,
      "DesignId": 4095,
      "PriceStr": "",
      "PriceWithTaxStr": "",
      "ItemUnavailable": false,
      "UnavailableLink": null,
      "UnavailableReason": null
    },
    {
      "ItemNo": 4211461,
      "ItemDescr": "HINGE 1X2 LOWER PART",
      "ColourLikeDescr": "Grey",
      "ColourDescr": "MED. ST-GREY",
      "MaingroupDescr": "Bricks, Special",
      "Asset": "/media/bricks/5/2/4211461.jpg",
      "MaxQty": 200,
      "Ip": false,
      "Price": 0.18,
      "CId": "GBP",
      "SQty": 690,
      "DesignId": 3831,
      "PriceStr": "GBP 0.18",
      "PriceWithTaxStr": "GBP 0.18",
      "ItemUnavailable": false,
      "UnavailableLink": null,
      "UnavailableReason": null
    },
    {
      "ItemNo": 4219256,
      "ItemDescr": "HINGE PLATE 1X2 UN./OVER",
      "ColourLikeDescr": "Grey",
      "ColourDescr": "MED. ST-GREY",
      "MaingroupDescr": "Bricks, Special",
      "Asset": "/media/bricks/5/2/4219256.jpg",
      "MaxQty": 200,
      "Ip": false,
      "Price": 0.43,
      "CId": "GBP",
      "SQty": 209151,
      "DesignId": 73983,
      "PriceStr": "GBP 0.43",
      "PriceWithTaxStr": "GBP 0.43",
      "ItemUnavailable": false,
      "UnavailableLink": null,
      "UnavailableReason": null
    },
    {
      "ItemNo": 4211419,
      "ItemDescr": "COUPLING PLATE 2X2",
      "ColourLikeDescr": "Grey",
      "ColourDescr": "MED. ST-GREY",
      "MaingroupDescr": "Bricks, Special",
      "Asset": "/media/bricks/5/2/4211419.jpg",
      "MaxQty": 200,
      "Ip": false,
      "Price": 0.13,
      "CId": "GBP",
      "SQty": 644,
      "DesignId": 3176,
      "PriceStr": "GBP 0.13",
      "PriceWithTaxStr": "GBP 0.13",
      "ItemUnavailable": false,
      "UnavailableLink": null,
      "UnavailableReason": null
    },
    {
      "ItemNo": 4211611,
      "ItemDescr": "HOOVERBOARD 6X6X2/3",
      "ColourLikeDescr": "Grey",
      "ColourDescr": "MED. ST-GREY",
      "MaingroupDescr": "Bricks, Special",
      "Asset": "/media/bricks/5/2/4211611.jpg",
      "MaxQty": 200,
      "Ip": false,
      "Price": -1,
      "CId": "GBP",
      "SQty": 0,
      "DesignId": 30303,
      "PriceStr": "",
      "PriceWithTaxStr": "",
      "ItemUnavailable": false,
      "UnavailableLink": null,
      "UnavailableReason": null
    },
    {
      "ItemNo": 4260409,
      "ItemDescr": "BRICK W. BOW 4X1X1 1/3",
      "ColourLikeDescr": "Grey",
      "ColourDescr": "MED. ST-GREY",
      "MaingroupDescr": "Bricks, Special",
      "Asset": "/media/bricks/5/2/4260409.jpg",
      "MaxQty": 200,
      "Ip": false,
      "Price": 0.29,
      "CId": "GBP",
      "SQty": 4516,
      "DesignId": 6081,
      "PriceStr": "GBP 0.29",
      "PriceWithTaxStr": "GBP 0.29",
      "ItemUnavailable": false,
      "UnavailableLink": null,
      "UnavailableReason": null
    },
    {
      "ItemNo": 4211464,
      "ItemDescr": "MINI HANDLE",
      "ColourLikeDescr": "Grey",
      "ColourDescr": "MED. ST-GREY",
      "MaingroupDescr": "Bricks, Special",
      "Asset": "/media/bricks/5/2/4211464.jpg",
      "MaxQty": 200,
      "Ip": false,
      "Price": 0.13,
      "CId": "GBP",
      "SQty": 991,
      "DesignId": 3839,
      "PriceStr": "GBP 0.13",
      "PriceWithTaxStr": "GBP 0.13",
      "ItemUnavailable": false,
      "UnavailableLink": null,
      "UnavailableReason": null
    },
    {
      "ItemNo": 4210633,
      "ItemDescr": "ROUND PLATE 1X1",
      "ColourLikeDescr": "Grey",
      "ColourDescr": "DK. ST. GREY",
      "MaingroupDescr": "Bricks, Special",
      "Asset": "/media/bricks/5/2/4210633.jpg",
      "MaxQty": 200,
      "Ip": false,
      "Price": 0.04,
      "CId": "GBP",
      "SQty": 95922,
      "DesignId": 6141,
      "PriceStr": "GBP 0.04",
      "PriceWithTaxStr": "GBP 0.04",
      "ItemUnavailable": false,
      "UnavailableLink": null,
      "UnavailableReason": null
    },
    {
      "ItemNo": 4260406,
      "ItemDescr": "BRICK 4X16 W/BOW/ANGLE",
      "ColourLikeDescr": "Grey",
      "ColourDescr": "DK. ST. GREY",
      "MaingroupDescr": "Bricks, Special",
      "Asset": "/media/bricks/5/2/4260406.jpg",
      "MaxQty": 200,
      "Ip": false,
      "Price": -1,
      "CId": "GBP",
      "SQty": 0,
      "DesignId": 45301,
      "PriceStr": "",
      "PriceWithTaxStr": "",
      "ItemUnavailable": false,
      "UnavailableLink": null,
      "UnavailableReason": null
    },
    {
      "ItemNo": 4211043,
      "ItemDescr": "PLATE 2X3",
      "ColourLikeDescr": "Grey",
      "ColourDescr": "DK. ST. GREY",
      "MaingroupDescr": "Bricks, Special",
      "Asset": "/media/bricks/5/2/4211043.jpg",
      "MaxQty": 200,
      "Ip": false,
      "Price": 0.11,
      "CId": "GBP",
      "SQty": 6957,
      "DesignId": 3021,
      "PriceStr": "GBP 0.11",
      "PriceWithTaxStr": "GBP 0.11",
      "ItemUnavailable": false,
      "UnavailableLink": null,
      "UnavailableReason": null
    },
    {
      "ItemNo": 4256149,
      "ItemDescr": "PLATE 6X12",
      "ColourLikeDescr": "Grey",
      "ColourDescr": "DK. ST. GREY",
      "MaingroupDescr": "Bricks, Special",
      "Asset": "/media/bricks/5/2/4256149.jpg",
      "MaxQty": 200,
      "Ip": false,
      "Price": 1,
      "CId": "GBP",
      "SQty": 641,
      "DesignId": 3028,
      "PriceStr": "GBP 1.00",
      "PriceWithTaxStr": "GBP 1.00",
      "ItemUnavailable": false,
      "UnavailableLink": null,
      "UnavailableReason": null
    },
    {
      "ItemNo": 4211115,
      "ItemDescr": "PLATE 4X6",
      "ColourLikeDescr": "Grey",
      "ColourDescr": "DK. ST. GREY",
      "MaingroupDescr": "Bricks, Special",
      "Asset": "/media/bricks/5/2/4211115.jpg",
      "MaxQty": 200,
      "Ip": false,
      "Price": 0.36,
      "CId": "GBP",
      "SQty": 1259,
      "DesignId": 3032,
      "PriceStr": "GBP 0.36",
      "PriceWithTaxStr": "GBP 0.36",
      "ItemUnavailable": false,
      "UnavailableLink": null,
      "UnavailableReason": null
    },
    {
      "ItemNo": 4210997,
      "ItemDescr": "PLATE 2X8",
      "ColourLikeDescr": "Grey",
      "ColourDescr": "DK. ST. GREY",
      "MaingroupDescr": "Bricks, Special",
      "Asset": "/media/bricks/5/2/4210997.jpg",
      "MaxQty": 200,
      "Ip": false,
      "Price": 0.24,
      "CId": "GBP",
      "SQty": 2466,
      "DesignId": 3034,
      "PriceStr": "GBP 0.24",
      "PriceWithTaxStr": "GBP 0.24",
      "ItemUnavailable": false,
      "UnavailableLink": null,
      "UnavailableReason": null
    },
    {
      "ItemNo": 4211001,
      "ItemDescr": "PLATE 1X4",
      "ColourLikeDescr": "Grey",
      "ColourDescr": "DK. ST. GREY",
      "MaingroupDescr": "Bricks, Special",
      "Asset": "/media/bricks/5/2/4211001.jpg",
      "MaxQty": 200,
      "Ip": false,
      "Price": 0.08,
      "CId": "GBP",
      "SQty": 11607,
      "DesignId": 3710,
      "PriceStr": "GBP 0.08",
      "PriceWithTaxStr": "GBP 0.08",
      "ItemUnavailable": false,
      "UnavailableLink": null,
      "UnavailableReason": null
    },
    {
      "ItemNo": 4222042,
      "ItemDescr": "PLATE 4X4, 1/4 CIRCLE",
      "ColourLikeDescr": "Grey",
      "ColourDescr": "DK. ST. GREY",
      "MaingroupDescr": "Bricks, Special",
      "Asset": "/media/bricks/5/2/4222042.jpg",
      "MaxQty": 200,
      "Ip": false,
      "Price": 0.2,
      "CId": "GBP",
      "SQty": 6179,
      "DesignId": 30565,
      "PriceStr": "GBP 0.20",
      "PriceWithTaxStr": "GBP 0.20",
      "ItemUnavailable": false,
      "UnavailableLink": null,
      "UnavailableReason": null
    },
    {
      "ItemNo": 4211063,
      "ItemDescr": "PLATE 1X2",
      "ColourLikeDescr": "Grey",
      "ColourDescr": "DK. ST. GREY",
      "MaingroupDescr": "Bricks, Special",
      "Asset": "/media/bricks/5/2/4211063.jpg",
      "MaxQty": 200,
      "Ip": false,
      "Price": 0.05,
      "CId": "GBP",
      "SQty": 10765,
      "DesignId": 3023,
      "PriceStr": "GBP 0.05",
      "PriceWithTaxStr": "GBP 0.05",
      "ItemUnavailable": false,
      "UnavailableLink": null,
      "UnavailableReason": null
    },
    {
      "ItemNo": 4211127,
      "ItemDescr": "ROOF TILE 2X4/45°",
      "ColourLikeDescr": "Grey",
      "ColourDescr": "DK. ST. GREY",
      "MaingroupDescr": "Bricks, Special",
      "Asset": "/media/bricks/5/2/4211127.jpg",
      "MaxQty": 200,
      "Ip": false,
      "Price": 0.19,
      "CId": "GBP",
      "SQty": 1753,
      "DesignId": 3037,
      "PriceStr": "GBP 0.19",
      "PriceWithTaxStr": "GBP 0.19",
      "ItemUnavailable": false,
      "UnavailableLink": null,
      "UnavailableReason": null
    },
    {
      "ItemNo": 4211088,
      "ItemDescr": "BRICK 1X2",
      "ColourLikeDescr": "Grey",
      "ColourDescr": "DK. ST. GREY",
      "MaingroupDescr": "Bricks, Special",
      "Asset": "/media/bricks/5/2/4211088.jpg",
      "MaxQty": 200,
      "Ip": false,
      "Price": 0.08,
      "CId": "GBP",
      "SQty": 16691,
      "DesignId": 3004,
      "PriceStr": "GBP 0.08",
      "PriceWithTaxStr": "GBP 0.08",
      "ItemUnavailable": false,
      "UnavailableLink": null,
      "UnavailableReason": null
    },
    {
      "ItemNo": 4221727,
      "ItemDescr": "ROTATION UPPER P.",
      "ColourLikeDescr": "Grey",
      "ColourDescr": "DK. ST. GREY",
      "MaingroupDescr": "Bricks, Special",
      "Asset": "/media/bricks/4/2/4221727.jpg",
      "MaxQty": 200,
      "Ip": false,
      "Price": -1,
      "CId": "GBP",
      "SQty": 0,
      "DesignId": 48289,
      "PriceStr": "",
      "PriceWithTaxStr": "",
      "ItemUnavailable": false,
      "UnavailableLink": null,
      "UnavailableReason": null
    },
    {
      "ItemNo": 4257734,
      "ItemDescr": "ROTATION BOTTOM WITHOUT ARM",
      "ColourLikeDescr": "Grey",
      "ColourDescr": "DK. ST. GREY",
      "MaingroupDescr": "Bricks, Special",
      "Asset": "/media/bricks/4/2/4257734.jpg",
      "MaxQty": 200,
      "Ip": false,
      "Price": -1,
      "CId": "GBP",
      "SQty": 0,
      "DesignId": 51219,
      "PriceStr": "",
      "PriceWithTaxStr": "",
      "ItemUnavailable": false,
      "UnavailableLink": null,
      "UnavailableReason": null
    },
    {
      "ItemNo": 4211067,
      "ItemDescr": "PLATE 2X12",
      "ColourLikeDescr": "Grey",
      "ColourDescr": "DK. ST. GREY",
      "MaingroupDescr": "Bricks, Special",
      "Asset": "/media/bricks/5/2/4211067.jpg",
      "MaxQty": 200,
      "Ip": false,
      "Price": 0.47,
      "CId": "GBP",
      "SQty": 979,
      "DesignId": 2445,
      "PriceStr": "GBP 0.47",
      "PriceWithTaxStr": "GBP 0.47",
      "ItemUnavailable": false,
      "UnavailableLink": null,
      "UnavailableReason": null
    },
    {
      "ItemNo": 4211122,
      "ItemDescr": "PLATE 4X10",
      "ColourLikeDescr": "Grey",
      "ColourDescr": "DK. ST. GREY",
      "MaingroupDescr": "Bricks, Special",
      "Asset": "/media/bricks/5/2/4211122.jpg",
      "MaxQty": 200,
      "Ip": false,
      "Price": 0.67,
      "CId": "GBP",
      "SQty": 989,
      "DesignId": 3030,
      "PriceStr": "GBP 0.67",
      "PriceWithTaxStr": "GBP 0.67",
      "ItemUnavailable": false,
      "UnavailableLink": null,
      "UnavailableReason": null
    },
    {
      "ItemNo": 4211134,
      "ItemDescr": "PLATE 6X6",
      "ColourLikeDescr": "Grey",
      "ColourDescr": "DK. ST. GREY",
      "MaingroupDescr": "Bricks, Special",
      "Asset": "/media/bricks/5/2/4211134.jpg",
      "MaxQty": 200,
      "Ip": false,
      "Price": 0.59,
      "CId": "GBP",
      "SQty": 1135,
      "DesignId": 3958,
      "PriceStr": "GBP 0.59",
      "PriceWithTaxStr": "GBP 0.59",
      "ItemUnavailable": false,
      "UnavailableLink": null,
      "UnavailableReason": null
    },
    {
      "ItemNo": 4221729,
      "ItemDescr": "ROT. DISC FOR CHAIR TOP",
      "ColourLikeDescr": "Grey",
      "ColourDescr": "DK. ST. GREY",
      "MaingroupDescr": "Bricks, Special",
      "Asset": "/media/bricks/4/2/4221729.jpg",
      "MaxQty": 200,
      "Ip": false,
      "Price": -1,
      "CId": "GBP",
      "SQty": 0,
      "DesignId": 48291,
      "PriceStr": "",
      "PriceWithTaxStr": "",
      "ItemUnavailable": false,
      "UnavailableLink": null,
      "UnavailableReason": null
    },
    {
      "ItemNo": 370526,
      "ItemDescr": "CROSS AXLE 4M",
      "ColourLikeDescr": "Black",
      "ColourDescr": "BLACK",
      "MaingroupDescr": "Bricks, Special Circles And Angles",
      "Asset": "/media/bricks/5/2/370526.jpg",
      "MaxQty": 200,
      "Ip": false,
      "Price": 0.08,
      "CId": "GBP",
      "SQty": 18328,
      "DesignId": 3705,
      "PriceStr": "GBP 0.08",
      "PriceWithTaxStr": "GBP 0.08",
      "ItemUnavailable": false,
      "UnavailableLink": null,
      "UnavailableReason": null
    },
    {
      "ItemNo": 4162857,
      "ItemDescr": "TECHNIC CROSS BLOCK/FORK 2X2",
      "ColourLikeDescr": "Black",
      "ColourDescr": "BLACK",
      "MaingroupDescr": "Bricks, Special Circles And Angles",
      "Asset": "/media/bricks/5/2/4162857.jpg",
      "MaxQty": 200,
      "Ip": false,
      "Price": 0.23,
      "CId": "GBP",
      "SQty": 1000,
      "DesignId": 41678,
      "PriceStr": "GBP 0.23",
      "PriceWithTaxStr": "GBP 0.23",
      "ItemUnavailable": false,
      "UnavailableLink": null,
      "UnavailableReason": null
    },
    {
      "ItemNo": 4233937,
      "ItemDescr": "CROSS AXLE 32M",
      "ColourLikeDescr": "Black",
      "ColourDescr": "BLACK",
      "MaingroupDescr": "Bricks, Special Circles And Angles",
      "Asset": "/media/bricks/5/2/4233937.jpg",
      "MaxQty": 200,
      "Ip": false,
      "Price": 2.72,
      "CId": "GBP",
      "SQty": 2011,
      "DesignId": 50450,
      "PriceStr": "GBP 2.72",
      "PriceWithTaxStr": "GBP 2.72",
      "ItemUnavailable": false,
      "UnavailableLink": null,
      "UnavailableReason": null
    },
    {
      "ItemNo": 4109810,
      "ItemDescr": "2M CROSS AXLE W. GROOVE",
      "ColourLikeDescr": "Black",
      "ColourDescr": "BLACK",
      "MaingroupDescr": "Bricks, Special Circles And Angles",
      "Asset": "/media/bricks/5/2/4109810.jpg",
      "MaxQty": 200,
      "Ip": false,
      "Price": 0.08,
      "CId": "GBP",
      "SQty": 11542,
      "DesignId": 32062,
      "PriceStr": "GBP 0.08",
      "PriceWithTaxStr": "GBP 0.08",
      "ItemUnavailable": false,
      "UnavailableLink": null,
      "UnavailableReason": null
    },
    {
      "ItemNo": 4163625,
      "ItemDescr": "CROSS AXLE, EXTENSION M/3 RIBS",
      "ColourLikeDescr": "Red",
      "ColourDescr": "TR.RED",
      "MaingroupDescr": "Bricks, Special Circles And Angles",
      "Asset": "/media/bricks/5/2/4163625.jpg",
      "MaxQty": 200,
      "Ip": false,
      "Price": -1,
      "CId": "GBP",
      "SQty": 0,
      "DesignId": 6538,
      "PriceStr": "",
      "PriceWithTaxStr": "",
      "ItemUnavailable": false,
      "UnavailableLink": null,
      "UnavailableReason": null
    },
    {
      "ItemNo": 4211550,
      "ItemDescr": "ANGLE ELEMENT, 0 DEGREES [1]",
      "ColourLikeDescr": "Grey",
      "ColourDescr": "MED. ST-GREY",
      "MaingroupDescr": "Bricks, Special Circles And Angles",
      "Asset": "/media/bricks/5/2/4211550.jpg",
      "MaxQty": 200,
      "Ip": false,
      "Price": 0.1,
      "CId": "GBP",
      "SQty": 607,
      "DesignId": 32013,
      "PriceStr": "GBP 0.10",
      "PriceWithTaxStr": "GBP 0.10",
      "ItemUnavailable": false,
      "UnavailableLink": null,
      "UnavailableReason": null
    },
    {
      "ItemNo": 4211483,
      "ItemDescr": "CONNECTOR PEG W. KNOB",
      "ColourLikeDescr": "Grey",
      "ColourDescr": "MED. ST-GREY",
      "MaingroupDescr": "Bricks, Special Circles And Angles",
      "Asset": "/media/bricks/5/2/4211483.jpg",
      "MaxQty": 200,
      "Ip": false,
      "Price": 0.07,
      "CId": "GBP",
      "SQty": 1014,
      "DesignId": 4274,
      "PriceStr": "GBP 0.07",
      "PriceWithTaxStr": "GBP 0.07",
      "ItemUnavailable": false,
      "UnavailableLink": null,
      "UnavailableReason": null
    },
    {
      "ItemNo": 4211573,
      "ItemDescr": "1/2 BUSH",
      "ColourLikeDescr": "Grey",
      "ColourDescr": "MED. ST-GREY",
      "MaingroupDescr": "Bricks, Special Circles And Angles",
      "Asset": "/media/bricks/5/2/4211573.jpg",
      "MaxQty": 200,
      "Ip": false,
      "Price": -1,
      "CId": "GBP",
      "SQty": 0,
      "DesignId": 32123,
      "PriceStr": "",
      "PriceWithTaxStr": "",
      "ItemUnavailable": false,
      "UnavailableLink": null,
      "UnavailableReason": null
    },
    {
      "ItemNo": 4211539,
      "ItemDescr": "CONICAL WHEEL Z12",
      "ColourLikeDescr": "Grey",
      "ColourDescr": "MED. ST-GREY",
      "MaingroupDescr": "Bricks, Special Circles And Angles",
      "Asset": "/media/bricks/5/2/4211539.jpg",
      "MaxQty": 200,
      "Ip": false,
      "Price": -1,
      "CId": "GBP",
      "SQty": 0,
      "DesignId": 6589,
      "PriceStr": "",
      "PriceWithTaxStr": "",
      "ItemUnavailable": false,
      "UnavailableLink": null,
      "UnavailableReason": null
    },
    {
      "ItemNo": 4211375,
      "ItemDescr": "BALL W. CROSS AXLE",
      "ColourLikeDescr": "Grey",
      "ColourDescr": "MED. ST-GREY",
      "MaingroupDescr": "Bricks, Special Circles And Angles",
      "Asset": "/media/bricks/5/2/4211375.jpg",
      "MaxQty": 200,
      "Ip": false,
      "Price": 0.16,
      "CId": "GBP",
      "SQty": 706,
      "DesignId": 2736,
      "PriceStr": "GBP 0.16",
      "PriceWithTaxStr": "GBP 0.16",
      "ItemUnavailable": false,
      "UnavailableLink": null,
      "UnavailableReason": null
    },
    {
      "ItemNo": 4211815,
      "ItemDescr": "CROSS AXLE 3M",
      "ColourLikeDescr": "Grey",
      "ColourDescr": "MED. ST-GREY",
      "MaingroupDescr": "Bricks, Special Circles And Angles",
      "Asset": "/media/bricks/5/2/4211815.jpg",
      "MaxQty": 200,
      "Ip": false,
      "Price": 0.06,
      "CId": "GBP",
      "SQty": 9928,
      "DesignId": 4519,
      "PriceStr": "GBP 0.06",
      "PriceWithTaxStr": "GBP 0.06",
      "ItemUnavailable": false,
      "UnavailableLink": null,
      "UnavailableReason": null
    },
    {
      "ItemNo": 4211086,
      "ItemDescr": "CROSSAXLE 3M WITH KNOB",
      "ColourLikeDescr": "Grey",
      "ColourDescr": "DK. ST. GREY",
      "MaingroupDescr": "Bricks, Special Circles And Angles",
      "Asset": "/media/bricks/5/2/4211086.jpg",
      "MaxQty": 200,
      "Ip": false,
      "Price": -1,
      "CId": "GBP",
      "SQty": -87,
      "DesignId": 6587,
      "PriceStr": "",
      "PriceWithTaxStr": "",
      "ItemUnavailable": false,
      "UnavailableLink": null,
      "UnavailableReason": null
    }
  ],
  "ImageBaseUrl": "https://lc-www-live-s.legocdn.com",
  "UnAvailableInformation": null
}